t6rcon/__init__.py
t6rcon/exceptions.py
t6rcon/rcon.py
t6rcon/core/__init__.py
t6rcon/core/constants.py
t6rcon/core/models.py
t6rcon-0.1.2.dist-info/licenses/LICENSE
t6rcon-0.1.2.dist-info/METADATA
t6rcon-0.1.2.dist-info/WHEEL
t6rcon-0.1.2.dist-info/top_level.txt
t6rcon-0.1.2.dist-info/RECORD
